[
  {
    "tier": "$5 a month",
    "sponsor": "sabberworm"
  },
  {
    "tier": "$5 a month",
    "sponsor": "calendee"
  },
  {
    "tier": "$5 a month",
    "sponsor": "kylewelsby"
  },
  {
    "tier": "$5 a month",
    "sponsor": "tinjaw"
  },
  {
    "tier": "$5 a month",
    "sponsor": "ricdex"
  },
  {
    "tier": "$49 a month",
    "sponsor": "Illyism"
  },
  {
    "tier": "$5 a month",
    "sponsor": "lexifdev"
  },
  {
    "tier": "$5 a month",
    "sponsor": "tacowaco"
  },
  {
    "tier": "$5 a month",
    "sponsor": "kachar"
  },
  {
    "tier": "$19 a month",
    "sponsor": "tpberntsen"
  },
  {
    "tier": "$5 a month",
    "sponsor": "zeluizr"
  },
  {
    "tier": "$5 a month",
    "sponsor": "AndersGerner"
  },
  {
    "tier": "$5 a month",
    "sponsor": "stopyellingatme"
  },
  {
    "tier": "$19 a month",
    "sponsor": "Marviel"
  },
  {
    "tier": "$19 a month",
    "sponsor": "bookofdom"
  },
  {
    "tier": "$5 a month",
    "sponsor": "juzhiyuan"
  },
  {
    "tier": "$5 a month",
    "sponsor": "gregaltuna"
  },
  {
    "tier": "$5 a month",
    "sponsor": "ctwhome"
  },
  {
    "tier": "$5 a month",
    "sponsor": "alienzz"
  },
  {
    "tier": "$5 a month",
    "sponsor": "zlwaterfield"
  },
  {
    "tier": "$5 a month",
    "sponsor": "Aaron-A"
  },
  {
    "tier": "$5 a month",
    "sponsor": "gabrielmip"
  },
  {
    "tier": "$5 a month",
    "sponsor": "glassmonkey"
  },
  {
    "tier": "$5 a month",
    "sponsor": "zoutiyx"
  },
  {
    "tier": "$5 a month",
    "sponsor": "adammoyle"
  },
  {
    "tier": "$5 a month",
    "sponsor": "EvonuX"
  },
  {
    "tier": "$5 a month",
    "sponsor": "KoreyPeters"
  },
  {
    "tier": "$49 a month",
    "sponsor": "ymmtshny"
  },
  {
    "tier": "$19 a month",
    "sponsor": "fefurst"
  },
  {
    "tier": "$5 a month",
    "sponsor": "sebastianbachmann"
  },
  {
    "tier": "$5 a month",
    "sponsor": "jvieirar"
  },
  {
    "tier": "$19 a month",
    "sponsor": "dshukertjr"
  },
  {
    "tier": "$5 a month",
    "sponsor": "CmplxStack"
  },
  {
    "tier": "$5 a month",
    "sponsor": "davilico05"
  },
  {
    "tier": "$19 a month",
    "sponsor": "Kunstderfug"
  },
  {
    "tier": "$5 a month",
    "sponsor": "hyochan"
  },
  {
    "tier": "$5 a month",
    "sponsor": "chunterb"
  },
  {
    "tier": "$5 a month",
    "sponsor": "madebyfabian"
  },
  {
    "tier": "$5 a month",
    "sponsor": "jwanner83"
  },
  {
    "tier": "$5 a month",
    "sponsor": "herbievine"
  },
  {
    "tier": "$5 a month",
    "sponsor": "Lucostus"
  },
  {
    "tier": "$19 a month",
    "sponsor": "peachp"
  },
  {
    "tier": "$5 a month",
    "sponsor": "killshot13"
  },
  {
    "tier": "$19 a month",
    "sponsor": "d-mok"
  },
  {
    "tier": "$19 a month",
    "sponsor": "lIIIIIIIIIIIIIIIIIIIII"
  },
  {
    "tier": "$5 a month",
    "sponsor": "yujong-lee"
  },
  {
    "tier": "$5 a month",
    "sponsor": "gregdenson"
  },
  {
    "tier": "$5 a month",
    "sponsor": "LeDragunov"
  },
  {
    "tier": "$49 a month",
    "sponsor": "CryptoJobsList"
  }
]
